{
  "size": [
    1000.0,
    1000.0
  ],
  "planets": [
    {
      "object": {
        "location": [
          500.0,
          500.0
        ],
        "radius": 30.0,
        "mass": -20000000.0,
        "velocity": [
          0.0,
          0.0
        ],
        "acceleration": [
          0.0,
          0.0
        ]
      }
    },
    {
      "object": {
        "location": [
          800.0,
          800.0
        ],
        "radius": 30.0,
        "mass": 62500000.0,
        "velocity": [
          0.0,
          0.0
        ],
        "acceleration": [
          0.0,
          0.0
        ]
      }
    },
    {
      "object": {
        "location": [
          200.0,
          200.0
        ],
        "radius": 30.0,
        "mass": 62500000.0,
        "velocity": [
          0.0,
          0.0
        ],
        "acceleration": [
          0.0,
          0.0
        ]
      }
    },
    {
      "object": {
        "location": [
          200.0,
          800.0
        ],
        "radius": 30.0,
        "mass": 62500000.0,
        "velocity": [
          0.0,
          0.0
        ],
        "acceleration": [
          0.0,
          0.0
        ]
      }
    },
    {
      "object": {
        "location": [
          800.0,
          200.0
        ],
        "radius": 30.0,
        "mass": 62500000.0,
        "velocity": [
          0.0,
          0.0
        ],
        "acceleration": [
          0.0,
          0.0
        ]
      }
    },
    {
      "object": {
        "location": [
          250.0,
          500.0
        ],
        "radius": 10.0,
        "mass": 1.0,
        "velocity": [
          0.0,
          500.0
        ],
        "acceleration": [
          0.0,
          0.0
        ]
      }
    }
  ],
  "ships": [],
  "bullets": []
}